lighthouse_garden/__init__.py
lighthouse_garden/__main__.py
lighthouse_garden/illuminate.py
lighthouse_garden/info.py
lighthouse_garden/export/__init__.py
lighthouse_garden/export/render.py
lighthouse_garden/lighthouse/__init__.py
lighthouse_garden/lighthouse/database.py
lighthouse_garden/lighthouse/interpreter.py
lighthouse_garden/lighthouse/process.py
lighthouse_garden/lighthouse/utility.py
lighthouse_garden/templates/index.html.j2
lighthouse_garden/templates/assets/tower.svg
lighthouse_garden/templates/assets/css/percentage.css
lighthouse_garden/templates/assets/css/style.css
lighthouse_garden/templates/assets/js/graph.js
lighthouse_garden/templates/assets/js/highlight.js
lighthouse_garden/templates/assets/js/modal.js
lighthouse_garden/templates/assets/js/time.js
lighthouse_garden/templates/assets/js/tooltip.js
lighthouse_garden/templates/partials/circle.html.j2
lighthouse_garden/templates/partials/info.html.j2
lighthouse_garden/templates/partials/item.html.j2
lighthouse_garden/templates/partials/trend.html.j2
lighthouse_garden/utility/__init__.py
lighthouse_garden/utility/info.py
lighthouse_garden/utility/output.py
lighthouse_garden/utility/system.py
lighthouse_garden_kmi-1.3.1.dist-info/METADATA
lighthouse_garden_kmi-1.3.1.dist-info/WHEEL
lighthouse_garden_kmi-1.3.1.dist-info/entry_points.txt
lighthouse_garden_kmi-1.3.1.dist-info/top_level.txt
lighthouse_garden_kmi-1.3.1.dist-info/RECORD
