Metadata-Version: 2.1
Name: lighthouse-garden-kmi
Version: 1.3.1
Summary: Monitoring performance data by Google Lighthouse.
Home-page: https://github.com/jackd248/lighthouse-garden
Author: Konrad Michalik
Author-email: support@konradmichalik.eu
License: MIT
Classifier: Programming Language :: Python :: 3.5
Classifier: Programming Language :: Python :: 3.6
Classifier: Programming Language :: Python :: 3.7
Classifier: Programming Language :: Python :: 3.8
Classifier: Development Status :: 5 - Production/Stable
Classifier: License :: OSI Approved :: MIT License
Classifier: Operating System :: MacOS :: MacOS X
Classifier: Operating System :: Microsoft :: Windows
Classifier: Operating System :: POSIX
Classifier: Intended Audience :: Developers
Requires-Python: >=3.5
Requires-Dist: future-fstrings >=1.2
Requires-Dist: Jinja2 >=2.11.2
Requires-Dist: anybadge >=1.7.0
